square/__init__.py
square/__main__.py
pytonme101-1.0.dist-info/LICENSE
pytonme101-1.0.dist-info/METADATA
pytonme101-1.0.dist-info/WHEEL
pytonme101-1.0.dist-info/entry_points.txt
pytonme101-1.0.dist-info/top_level.txt
pytonme101-1.0.dist-info/RECORD
