Metadata-Version: 2.1
Name: pytonme101
Version: 1.0
Summary: It squares the number
Home-page: https://github.com/ruelagnes111/pytonme101
Author: Ruel Agnes
Author-email: ruelagnes101@gmail.com
License: MIT
Platform: UNKNOWN
Classifier: License :: OSI Approved :: MIT License
Classifier: Programming Language :: Python :: 3.6
Classifier: Programming Language :: Python :: 3.7
Classifier: Programming Language :: Python :: 3.8
